RTL/SCSI_SM/scsi_sm_outputs.v
 /*
// 
// Copyright (C) 2022  Mike Taylor
// This file is part of RE-SDMAC <https://github.com/mbtaylor1982/RE-SDMAC>.
// 
// RE-SDMAC is free software: you can redistribute it and/or modify
// it under the terms of the GNU General Public License as published by
// the Free Software Foundation, either version 3 of the License, or
// (at your option) any later version.
// 
// RE-SDMAC is distributed in the hope that it will be useful,
// but WITHOUT ANY WARRANTY; without even the implied warranty of
// MERCHANTABILITY or FITNESS FOR A PARTICULAR PURPOSE.  See the
// GNU General Public License for more details.
// 
// You should have received a copy of the GNU General Public License
// along with dogtag.  If not, see <http://www.gnu.org/licenses/>.
 */

module scsi_sm_outputs  (
  input [27:0] E_,
  
  output DACK,
  output INCBO,
  output INCNI,
  output INCNO,
  output RE,
  output WE,
  output SCSI_CS,
  output SET_DSACK,
  output S2F,
  output F2S,
  output S2CPU,
  output CPU2S,
  output [4:0] NEXT_STATE
);

  wire scsidff1_d;
  wire scsidff2_d;
  wire scsidff3_d;
  wire scsidff4_d;
  wire scsidff5_d;

  wire E0_;
  wire E1_;
  wire E2_;
  wire E3_;
  wire E4_;
  wire E5_;
  wire E6_;
  wire E7_;
  wire E8_;
  wire E9_;
  wire E10_;
  wire E11_;
  wire E12_;
  wire E13_;
  wire E14_;
  wire E15_;
  wire E16_;
  wire E17_;
  wire E18_;
  wire E19_;
  wire E20_;
  wire E21_;
  wire E22_;
  wire E23_;
  wire E24_;
  wire E25_;
  wire E26_;
  wire E27_;

  assign E0_ = E_[0];
  assign E1_ = E_[1];
  assign E2_ = E_[2];
  assign E3_ = E_[3];
  assign E4_ = E_[4];
  assign E5_ = E_[5];
  assign E6_ = E_[6];
  assign E7_ = E_[7];
  assign E8_ = E_[8];
  assign E9_ = E_[8];
  assign E10_ = E_[10];
  assign E11_ = E_[11];
  assign E12_ = E_[12];
  assign E13_ = E_[13];
  assign E14_ = E_[14];
  assign E15_ = E_[15];
  assign E16_ = E_[16];
  assign E17_ = E_[17];
  assign E18_ = E_[18];
  assign E19_ = E_[19];
  assign E20_ = E_[20];
  assign E21_ = E_[21];
  assign E22_ = E_[22];
  assign E23_ = E_[23];
  assign E24_ = E_[24];
  assign E25_ = E_[25];
  assign E26_ = E_[26];
  assign E27_ = E_[27];


  assign scsidff1_d = ~ (E17_ & E19_ & E23_ & E25_ & E26_ & E8_ & E9_);
  assign scsidff2_d = ~ (~ (E12_ & E13_ & E14_ & E15_ & E16_ & E17_) | ~ (E18_ & E22_ & E24_ & E26_ & E27_));
  assign scsidff3_d = ~ (~ (E0_ & E14_ & E2_ & E7_) | ~ (E15_ & E18_ & E20_ & E21_ & E22_ & E27_));
  assign scsidff4_d = ~ (~ (E0_ & E12_ & E14_ & E15_ & E1_ & E6_) | ~ (E19_ & E20_ & E23_ & E24_ & E25_ & E27_));
  assign scsidff5_d = ~ (~ (E11_ & E13_ & E19_ & E1_ & E5_ & E8_) | ~ (E21_ & E22_ & E23_ & E24_ & E26_ & E27_));

  assign NEXT_STATE = {scsidff5_d, scsidff4_d, scsidff3_d, scsidff2_d, scsidff1_d};
  
  assign DACK = ~ (E0_ & E13_ & E16_ & E1_ & E20_ & E21_ & E7_ & E9_);
  assign INCBO = ~ (E10_ & E11_);
  assign INCNI = ~ (E2_ & E4_);
  assign INCNO = ~ (E2_ & E3_);
  assign RE = ~ (E12_ & E17_ & E20_ & E21_ & E25_ & E26_ & E27_ & E7_);
  assign WE = ~ (E13_ & E16_ & E18_ & E24_ & E8_ & E9_);
  assign SCSI_CS = ~ (~ (E12_ & E17_ & E18_ & E8_) | ~ (E22_ & E24_ & E25_ & E26_ & E27_));
  assign SET_DSACK = ~ (E22_ & E25_);
  assign S2F = ~ (E10_ & E20_ & E21_ & E7_);
  assign F2S = ~ (E11_ & E13_ & E16_ & E9_);
  assign S2CPU = ~ (E12_ & E17_ & E19_ & E23_ & E25_ & E26_ & E27_);
  assign CPU2S = ~ (E18_ & E22_ & E24_ & E8_);

endmodule

RTL/SCSI_SM/scsi_sm_inputs.v
 /*
// 
// Copyright (C) 2022  Mike Taylor
// This file is part of RE-SDMAC <https://github.com/mbtaylor1982/RE-SDMAC>.
// 
// RE-SDMAC is free software: you can redistribute it and/or modify
// it under the terms of the GNU General Public License as published by
// the Free Software Foundation, either version 3 of the License, or
// (at your option) any later version.
// 
// RE-SDMAC is distributed in the hope that it will be useful,
// but WITHOUT ANY WARRANTY; without even the implied warranty of
// MERCHANTABILITY or FITNESS FOR A PARTICULAR PURPOSE.  See the
// GNU General Public License for more details.
// 
// You should have received a copy of the GNU General Public License
// along with dogtag.  If not, see <http://www.gnu.org/licenses/>.
 */

module scsi_sm_inputs(
  input [4:0] STATE,   
  input BOEQ3,
  input CCPUREQ,
  input CDREQ_,
  input CDSACK_,
  input DMADIR,
  input FIFOEMPTY,
  input FIFOFULL,
  input RDFIFO_o,
  input RIFIFO_o,
  input RW,

  output [27:0] E_
);
  wire nCDSACK_;
  wire nDMADIR;

  wire scsidff1_q;
  wire scsidff2_q;
  wire scsidff3_q;
  wire scsidff4_q;
  wire scsidff5_q; 
  
  wire nscsidff1_q;
  wire nscsidff2_q;
  wire nscsidff3_q;
  wire nscsidff4_q;
  wire nscsidff5_q;

  wire E0_;
  wire E1_;
  wire E2_;
  wire E3_;
  wire E4_;
  wire E5_;
  wire E6_;
  wire E7_;
  wire E8_;
  wire E9_;
  wire E10_;
  wire E11_;
  wire E12_;
  wire E13_;
  wire E14_;
  wire E15_;
  wire E16_;
  wire E17_;
  wire E18_;
  wire E19_;
  wire E20_;
  wire E21_;
  wire E22_;
  wire E23_;
  wire E24_;
  wire E25_;
  wire E26_;
  wire E27_;
    
  assign nCDSACK_ = ~ CDSACK_;
  assign nDMADIR = ~ DMADIR;

  assign scsidff1_q = STATE[0];
  assign scsidff2_q = STATE[1];
  assign scsidff3_q = STATE[2];
  assign scsidff4_q = STATE[3];
  assign scsidff5_q = STATE[4];

  assign nscsidff1_q = ~ scsidff1_q;
  assign nscsidff2_q = ~ scsidff2_q;
  assign nscsidff3_q = ~ scsidff3_q;
  assign nscsidff4_q = ~ scsidff4_q;
  assign nscsidff5_q = ~ scsidff5_q;

  assign E0_ = ~ (~ (CDREQ_ | FIFOEMPTY | DMADIR | CCPUREQ | RDFIFO_o | scsidff1_q | scsidff2_q | scsidff4_q) & scsidff5_q); //checked MT
  assign E1_ = ~ (~ (CDREQ_ | FIFOFULL | nDMADIR | CCPUREQ | RIFIFO_o | scsidff1_q | scsidff2_q | scsidff4_q) & nscsidff3_q & nscsidff5_q); //checked MT
  assign E2_ = ~ (FIFOFULL & nscsidff1_q & nscsidff2_q & nscsidff3_q & scsidff4_q & scsidff5_q); //checked MT
  assign E3_ = ~ (BOEQ3 & scsidff1_q & nscsidff2_q & nscsidff4_q & nscsidff5_q); //checked MT
  assign E4_ = ~ (BOEQ3 & nscsidff2_q & scsidff3_q & scsidff4_q & nscsidff5_q); //checked MT
  assign E5_ = ~ (nDMADIR & ~ CCPUREQ & nscsidff2_q & nscsidff3_q & nscsidff4_q); //checked MT
  assign E6_ = ~ (CCPUREQ & nscsidff1_q & nscsidff2_q & nscsidff3_q & nscsidff4_q); //checked MT
  assign E7_ = ~ (~ FIFOFULL & nscsidff1_q & nscsidff2_q & nscsidff3_q & scsidff4_q & scsidff5_q); //checked MT
  assign E8_ = ~ (~ RW & nscsidff1_q & nscsidff2_q & nscsidff3_q & scsidff4_q & nscsidff5_q); //checked MT
  assign E9_ = ~ (nscsidff1_q & scsidff2_q & nscsidff3_q & nscsidff4_q & scsidff5_q); //checked MT
  assign E10_ = ~ (nscsidff2_q & scsidff3_q & scsidff4_q & nscsidff5_q); //checked MT
  assign E11_ = ~ (scsidff1_q & nscsidff2_q & nscsidff4_q & nscsidff5_q); //checked MT
  assign E12_ = ~ (RW & nscsidff1_q & nscsidff3_q & scsidff4_q & nscsidff5_q); //checked MT
  assign E13_ = ~ (nscsidff1_q & scsidff2_q & nscsidff3_q & nscsidff4_q & nscsidff5_q); //checked MT
  assign E14_ = ~ (nCDSACK_ & scsidff2_q & scsidff4_q & nscsidff5_q); //checked MT
  assign E15_ = ~ (scsidff2_q & scsidff3_q & nscsidff4_q & scsidff5_q); //checked MT
  assign E16_ = ~ (nscsidff2_q & scsidff3_q & scsidff4_q & scsidff5_q); //checked MT
  assign E17_ = ~ (scsidff2_q & scsidff3_q & scsidff4_q & scsidff5_q); //checked MT
  assign E18_ = ~ (scsidff2_q & nscsidff3_q & scsidff4_q & scsidff5_q); //checked MT
  assign E19_ = ~ (nCDSACK_ & scsidff1_q & scsidff4_q); //checked MT
  assign E20_ = ~ (nscsidff2_q & scsidff3_q & nscsidff4_q & scsidff5_q); //checked MT
  assign E21_ = ~ (nscsidff2_q & scsidff3_q & nscsidff4_q & nscsidff5_q); //checked MT
  assign E22_ = ~ (scsidff2_q & scsidff3_q & nscsidff4_q & nscsidff5_q); //checked MT
  assign E23_ = ~ (scsidff1_q & scsidff4_q & nscsidff5_q); //checked MT
  assign E24_ = ~ (scsidff1_q & nscsidff2_q & nscsidff4_q & scsidff5_q); //checked MT
  assign E25_ = ~ (scsidff1_q & scsidff2_q & scsidff5_q); //checked MT
  assign E26_ = ~ (scsidff1_q & scsidff2_q & nscsidff5_q); //checked MT
  assign E27_ = ~ (scsidff2_q & nscsidff3_q & scsidff4_q & nscsidff5_q); //checked MT

  assign E_[27:0] = {E27_,E26_,E25_,E24_,E23_,E22_,E21_,E20_,E19_,E18_,E17_,E16_,E15_,E14_,E13_,E12_,E11_,E10_,E9_,E8_,E7_,E6_,E5_,E4_,E3_,E2_,E1_,E0_};
  
endmodule

RTL/SCSI_SM/SCSI_SM.v
 /*
// 
// Copyright (C) 2022  Mike Taylor
// This file is part of RE-SDMAC <https://github.com/mbtaylor1982/RE-SDMAC>.
// 
// RE-SDMAC is free software: you can redistribute it and/or modify
// it under the terms of the GNU General Public License as published by
// the Free Software Foundation, either version 3 of the License, or
// (at your option) any later version.
// 
// RE-SDMAC is distributed in the hope that it will be useful,
// but WITHOUT ANY WARRANTY; without even the implied warranty of
// MERCHANTABILITY or FITNESS FOR A PARTICULAR PURPOSE.  See the
// GNU General Public License for more details.
// 
// You should have received a copy of the GNU General Public License
// along with dogtag.  If not, see <http://www.gnu.org/licenses/>.
 */

 `include "RTL/SCSI_SM/scsi_sm_inputs.v"
 `include "RTL/SCSI_SM/scsi_sm_outputs.v"

module SCSI_SM(
    input CPUREQ,
    input RW,
    input DMADIR,   
    input INCFIFO,
    input DECFIFO, 
    input RESET_,
    input BOEQ3,
    input CPUCLK,
    input DREQ_,
    input FIFOFULL,
    input FIFOEMPTY,
    input nAS_,

    output SET_DSACK,
    output reg RDFIFO_d,
    output reg RIFIFO_d,
    output reg RE_o,
    output reg WE_o,
    output reg SCSI_CS_o,
    output reg DACK_o,
    output reg INCBO_o,
    output reg INCNO_o,
    output reg INCNI_o,
    output reg S2F_o,
    output reg F2S_o,
    output reg S2CPU_o,
    output reg CPU2S_o,
    output wire LS2CPU,
    output wire LBYTE_
);

localparam INITIAL_STATE = 5'b11110;

reg [4:0] STATE;

//Clocked inputs
reg CCPUREQ;
reg CDREQ_;
reg CDSACK_;
reg CRESET_;

wire DSACK_;
wire RE;
wire WE;
wire SCSI_CS;
wire DACK;
wire INCBO;
wire INCNO;
wire INCNI;
wire S2F;
wire F2S;
wire S2CPU;
wire CPU2S;

reg RDFIFO_o;
reg RIFIFO_o;
reg LS2CPU_;

wire RDRST_;
wire RIRST_;

wire nRW;
wire nDMADIR;
wire nFIFOFULL;
wire nCCPUREQ;
wire nCDREQ_;
wire nCDSACK_;

wire nCLK; // CPUCLK Inverted
wire BCLK; // CPUCLK Inverted 4 times for delay.
wire BBCLK; // CPUCLK Inverted 6 time for delay.

wire [27:0] E_;
wire [4:0] NEXT_STATE;

scsi_sm_inputs u_scsi_sm_inputs(
    .STATE      (STATE),
    .BOEQ3      (BOEQ3      ),
    .CCPUREQ    (CCPUREQ    ),
    .CDREQ_     (CDREQ_     ),
    .CDSACK_    (CDSACK_    ),
    .DMADIR     (DMADIR     ),
    .FIFOEMPTY  (FIFOEMPTY  ),
    .FIFOFULL   (FIFOFULL   ),
    .RDFIFO_o   (RDFIFO_o   ),
    .RIFIFO_o   (RIFIFO_o   ),
    .RW         (RW         ),
    .E_         (E_         )
);

scsi_sm_outputs u_scsi_sm_outputs(
    .E_         (E_         ),
    .NEXT_STATE (NEXT_STATE ), 
    .DACK       (DACK       ),
    .INCBO      (INCBO      ),
    .INCNI      (INCNI      ),
    .INCNO      (INCNO      ),
    .RE         (RE         ),
    .WE         (WE         ),
    .SCSI_CS    (SCSI_CS    ),
    .SET_DSACK  (SET_DSACK  ),
    .S2F        (S2F        ),
    .F2S        (F2S        ),
    .S2CPU      (S2CPU      ),
    .CPU2S      (CPU2S      )
);

//clocked reset
always @(posedge  nCLK) begin
    CRESET_ <= RESET_;

    if(RESET_ == 1'b0) begin     
        CDSACK_ <= 1'b0;
    end
end

//clocked inputs.
always @(posedge  BBCLK or negedge CRESET_) begin
    if (CRESET_ == 1'b0) 
        CDSACK_ <= 1'b0;
    else 
    begin
        CCPUREQ <= CPUREQ;
        CDREQ_ <= DREQ_;
        CDSACK_ <= DSACK_;   
    end
end

//Clocked outputs.
always @(posedge BCLK) begin
    RE_o <= RE;
    WE_o <= WE;
    SCSI_CS_o <= ~SCSI_CS;
    DACK_o <= DACK;
    INCBO_o <= INCBO;
    INCNO_o <= INCNO;
    INCNI_o <= INCNI;
    S2F_o <= S2F;
    F2S_o <= F2S;
    S2CPU_o <= S2CPU;
    CPU2S_o <= CPU2S;   
    RDFIFO_d <= ~E_[3];
    RIFIFO_d <=  ~E_[4];
end

//State Machine
always @(posedge BCLK or negedge CRESET_) begin
    if (CRESET_ == 1'b0) 
        STATE <= INITIAL_STATE;
    else
        STATE <= NEXT_STATE;
end


always @(posedge RDFIFO_d or negedge RDRST_) begin
    if (RDRST_ == 1'b0) 
        RDFIFO_o <= 1'b0;
    else
        RDFIFO_o <= 1'b1;
end


always @(posedge RIFIFO_d or negedge RIRST_) begin
    if (RIRST_ == 1'b0) 
        RIFIFO_o <= 1'b0;
    else
        RIFIFO_o <= 1'b1;
end

always @(posedge SET_DSACK or negedge nAS_) begin
    if (nAS_ == 1'b0)
        LS2CPU_ <= 1'b0;
    else
        LS2CPU_ <= 1'b1;
end

assign nCLK = ~CPUCLK;
assign BCLK = CPUCLK; // may need to change this to add delays
assign BBCLK = CPUCLK; // may need to change this to add delays

assign nRW = ~RW;
assign nDMADIR = ~DMADIR;
assign nFIFOFULL = ~FIFOFULL;
assign nCCPUREQ = ~CCPUREQ;
assign nCDREQ_ = ~CDREQ_;
assign nCDSACK_ = ~CDSACK_;
assign LS2CPU = ~LS2CPU_;
assign DSACK_ = LS2CPU;
assign LBYTE_ = ~(DACK_o & RE_o);

assign RDRST_ = ~(RESET_ | DECFIFO);
assign RIRST_ = ~(RESET_ | INCFIFO);


endmodule

RTL/SCSI_SM/Testbench/SCSI_SM_tb.v
 /*
// 
// Copyright (C) 2022  Mike Taylor
// This file is part of RE-SDMAC <https://github.com/mbtaylor1982/RE-SDMAC>.
// 
// RE-SDMAC is free software: you can redistribute it and/or modify
// it under the terms of the GNU General Public License as published by
// the Free Software Foundation, either version 3 of the License, or
// (at your option) any later version.
// 
// RE-SDMAC is distributed in the hope that it will be useful,
// but WITHOUT ANY WARRANTY; without even the implied warranty of
// MERCHANTABILITY or FITNESS FOR A PARTICULAR PURPOSE.  See the
// GNU General Public License for more details.
// 
// You should have received a copy of the GNU General Public License
// along with dogtag.  If not, see <http://www.gnu.org/licenses/>.
 */

`timescale 1ns/100ps

`include "RTL/SCSI_SM/SCSI_SM.v"

module scsi_sm_tb; 
//inputs
reg nAS_;
reg CPUREQ;
reg RW;
reg DMADIR;
reg INCFIFO;
reg DECFIFO;
reg RESET_;
reg BOEQ3;
reg CPUCLK;
reg DREQ_;
reg FIFOFULL;
reg FIFOEMPTY;

//Outputs
wire LS2CPU;
wire RDFIFO_d;
wire RIFIFO_d;
wire RE_o;
wire WE_o;
wire SCSI_CS_o;
wire DACK_o;
wire INCBO_o;
wire INCNO_o;
wire INCNI_o;
wire S2F_o;
wire F2S_o;
wire S2CPU_o;
wire CPU2S_o;


SCSI_SM u_SCSI_SM(
    .nAS_      (nAS_      ),
    .CPUREQ    (CPUREQ    ),
    .RW        (RW        ),
    .DMADIR    (DMADIR    ),
    .INCFIFO   (INCFIFO   ),
    .DECFIFO   (DECFIFO   ),
    .RESET_    (RESET_    ),
    .BOEQ3     (BOEQ3     ),
    .CPUCLK    (CPUCLK    ),
    .DREQ_     (DREQ_     ),
    .FIFOFULL  (FIFOFULL  ),
    .FIFOEMPTY (FIFOEMPTY ),
    .LS2CPU    (LS2CPU ),
    .RDFIFO_d  (RDFIFO_d  ),
    .RIFIFO_d  (RIFIFO_d  ),
    .RE_o      (RE_o      ),
    .WE_o      (WE_o      ),
    .SCSI_CS_o (SCSI_CS_o ),
    .DACK_o    (DACK_o    ),
    .INCBO_o   (INCBO_o   ),
    .INCNO_o   (INCNO_o   ),
    .INCNI_o   (INCNI_o   ),
    .S2F_o     (S2F_o     ),
    .F2S_o     (F2S_o     ),
    .S2CPU_o   (S2CPU_o   ),
    .CPU2S_o   (CPU2S_o   )
);

    initial begin
        $display("*Testing SDMAC SCSI_SM.v Module*");
        $dumpfile("../SCSI_SM/VCD/SCSI_SM_tb.vcd");
        $dumpvars(0, scsi_sm_tb);
        
        //test FIFO Full Empty Counter
        $display("Testing SCSI State Machine RESET");
        //set initial state
        CPUCLK = 1'b1;
        CPUREQ = 1'b1;
        RESET_ = 1'b1;
        nAS_ = 1'b0;
        RW = 1'b0;
        DMADIR = 1'b0;
        INCFIFO = 1'b0;
        DECFIFO = 1'b0;
        BOEQ3 = 1'b0;
        DREQ_ = 1'b1;
        FIFOFULL = 1'b0;
        FIFOEMPTY = 1'b1;
        repeat(2) #10 CPUCLK = ~CPUCLK;
        RESET_ = 1'b0;
        repeat(4) #10 CPUCLK = ~CPUCLK;
        RESET_ = 1'b1;
        nAS_ = 1'b1;
        repeat(32) #10 CPUCLK = ~CPUCLK;
        nAS_ = 1'b0;
        CPUREQ = 1'b0;
        repeat(16) #10 CPUCLK = ~CPUCLK;
        $finish;
    end 

endmodule

RTL/SCSI_SM/VCD/SCSI_SM_tb.vcd
$date
	Sun Nov 20 14:23:22 2022
$end
$version
	Icarus Verilog
$end
$timescale
	100ps
$end
$scope module scsi_sm_tb $end
$var wire 1 ! WE_o $end
$var wire 1 " SCSI_CS_o $end
$var wire 1 # S2F_o $end
$var wire 1 $ S2CPU_o $end
$var wire 1 % RIFIFO_d $end
$var wire 1 & RE_o $end
$var wire 1 ' RDFIFO_d $end
$var wire 1 ( LS2CPU $end
$var wire 1 ) INCNO_o $end
$var wire 1 * INCNI_o $end
$var wire 1 + INCBO_o $end
$var wire 1 , F2S_o $end
$var wire 1 - DACK_o $end
$var wire 1 . CPU2S_o $end
$var reg 1 / BOEQ3 $end
$var reg 1 0 CPUCLK $end
$var reg 1 1 CPUREQ $end
$var reg 1 2 DECFIFO $end
$var reg 1 3 DMADIR $end
$var reg 1 4 DREQ_ $end
$var reg 1 5 FIFOEMPTY $end
$var reg 1 6 FIFOFULL $end
$var reg 1 7 INCFIFO $end
$var reg 1 8 RESET_ $end
$var reg 1 9 RW $end
$var reg 1 : nAS_ $end
$scope module u_SCSI_SM $end
$var wire 1 ; BBCLK $end
$var wire 1 < BCLK $end
$var wire 1 / BOEQ3 $end
$var wire 1 0 CPUCLK $end
$var wire 1 1 CPUREQ $end
$var wire 1 2 DECFIFO $end
$var wire 1 3 DMADIR $end
$var wire 1 4 DREQ_ $end
$var wire 1 = DSACK_ $end
$var wire 1 5 FIFOEMPTY $end
$var wire 1 6 FIFOFULL $end
$var wire 1 7 INCFIFO $end
$var wire 1 > LBYTE_ $end
$var wire 1 ( LS2CPU $end
$var wire 1 ? RDRST_ $end
$var wire 1 8 RESET_ $end
$var wire 1 @ RIRST_ $end
$var wire 1 9 RW $end
$var wire 1 : nAS_ $end
$var wire 1 A nCCPUREQ $end
$var wire 1 B nCDREQ_ $end
$var wire 1 C nCDSACK_ $end
$var wire 1 D nCLK $end
$var wire 1 E nDMADIR $end
$var wire 1 F nFIFOFULL $end
$var wire 1 G nRW $end
$var wire 1 H WE $end
$var wire 1 I SET_DSACK $end
$var wire 1 J SCSI_CS $end
$var wire 1 K S2F $end
$var wire 1 L S2CPU $end
$var wire 1 M RE $end
$var wire 5 N NEXT_STATE [4:0] $end
$var wire 1 O INCNO $end
$var wire 1 P INCNI $end
$var wire 1 Q INCBO $end
$var wire 1 R F2S $end
$var wire 28 S E_ [27:0] $end
$var wire 1 T DACK $end
$var wire 1 U CPU2S $end
$var reg 1 V CCPUREQ $end
$var reg 1 W CDREQ_ $end
$var reg 1 X CDSACK_ $end
$var reg 1 . CPU2S_o $end
$var reg 1 Y CRESET_ $end
$var reg 1 - DACK_o $end
$var reg 1 , F2S_o $end
$var reg 1 + INCBO_o $end
$var reg 1 * INCNI_o $end
$var reg 1 ) INCNO_o $end
$var reg 1 Z LS2CPU_ $end
$var reg 1 ' RDFIFO_d $end
$var reg 1 [ RDFIFO_o $end
$var reg 1 & RE_o $end
$var reg 1 % RIFIFO_d $end
$var reg 1 \ RIFIFO_o $end
$var reg 1 $ S2CPU_o $end
$var reg 1 # S2F_o $end
$var reg 1 " SCSI_CS_o $end
$var reg 5 ] STATE [4:0] $end
$var reg 1 ! WE_o $end
$scope module u_scsi_sm_inputs $end
$var wire 1 / BOEQ3 $end
$var wire 1 V CCPUREQ $end
$var wire 1 W CDREQ_ $end
$var wire 1 X CDSACK_ $end
$var wire 1 3 DMADIR $end
$var wire 1 ^ E0_ $end
$var wire 1 _ E10_ $end
$var wire 1 ` E11_ $end
$var wire 1 a E12_ $end
$var wire 1 b E13_ $end
$var wire 1 c E14_ $end
$var wire 1 d E15_ $end
$var wire 1 e E16_ $end
$var wire 1 f E17_ $end
$var wire 1 g E18_ $end
$var wire 1 h E19_ $end
$var wire 1 i E1_ $end
$var wire 1 j E20_ $end
$var wire 1 k E21_ $end
$var wire 1 l E22_ $end
$var wire 1 m E23_ $end
$var wire 1 n E24_ $end
$var wire 1 o E25_ $end
$var wire 1 p E26_ $end
$var wire 1 q E27_ $end
$var wire 1 r E2_ $end
$var wire 1 s E3_ $end
$var wire 1 t E4_ $end
$var wire 1 u E5_ $end
$var wire 1 v E6_ $end
$var wire 1 w E7_ $end
$var wire 1 x E8_ $end
$var wire 1 y E9_ $end
$var wire 1 5 FIFOEMPTY $end
$var wire 1 6 FIFOFULL $end
$var wire 1 [ RDFIFO_o $end
$var wire 1 \ RIFIFO_o $end
$var wire 1 9 RW $end
$var wire 5 z STATE [4:0] $end
$var wire 1 { nCDSACK_ $end
$var wire 1 | nDMADIR $end
$var wire 1 } nscsidff1_q $end
$var wire 1 ~ nscsidff2_q $end
$var wire 1 !" nscsidff3_q $end
$var wire 1 "" nscsidff4_q $end
$var wire 1 #" nscsidff5_q $end
$var wire 1 $" scsidff5_q $end
$var wire 1 %" scsidff4_q $end
$var wire 1 &" scsidff3_q $end
$var wire 1 '" scsidff2_q $end
$var wire 1 (" scsidff1_q $end
$var wire 28 )" E_ [27:0] $end
$upscope $end
$scope module u_scsi_sm_outputs $end
$var wire 1 U CPU2S $end
$var wire 1 T DACK $end
$var wire 28 *" E_ [27:0] $end
$var wire 1 R F2S $end
$var wire 1 Q INCBO $end
$var wire 1 P INCNI $end
$var wire 1 O INCNO $end
$var wire 1 M RE $end
$var wire 1 L S2CPU $end
$var wire 1 K S2F $end
$var wire 1 J SCSI_CS $end
$var wire 1 I SET_DSACK $end
$var wire 1 H WE $end
$var wire 1 +" scsidff1_d $end
$var wire 1 ," scsidff2_d $end
$var wire 1 -" scsidff3_d $end
$var wire 1 ." scsidff4_d $end
$var wire 1 /" scsidff5_d $end
$var wire 5 0" NEXT_STATE [4:0] $end
$var wire 1 1" E9_ $end
$var wire 1 2" E8_ $end
$var wire 1 3" E7_ $end
$var wire 1 4" E6_ $end
$var wire 1 5" E5_ $end
$var wire 1 6" E4_ $end
$var wire 1 7" E3_ $end
$var wire 1 8" E2_ $end
$var wire 1 9" E27_ $end
$var wire 1 :" E26_ $end
$var wire 1 ;" E25_ $end
$var wire 1 <" E24_ $end
$var wire 1 =" E23_ $end
$var wire 1 >" E22_ $end
$var wire 1 ?" E21_ $end
$var wire 1 @" E20_ $end
$var wire 1 A" E1_ $end
$var wire 1 B" E19_ $end
$var wire 1 C" E18_ $end
$var wire 1 D" E17_ $end
$var wire 1 E" E16_ $end
$var wire 1 F" E15_ $end
$var wire 1 G" E14_ $end
$var wire 1 H" E13_ $end
$var wire 1 I" E12_ $end
$var wire 1 J" E11_ $end
$var wire 1 K" E10_ $end
$var wire 1 L" E0_ $end
$upscope $end
$upscope $end
$upscope $end
$enddefinitions $end
#0
$dumpvars
1L"
xK"
xJ"
1I"
xH"
xG"
xF"
xE"
xD"
xC"
xB"
1A"
x@"
x?"
x>"
x="
x<"
x;"
x:"
x9"
18"
17"
16"
15"
x4"
x3"
x2"
x1"
bx 0"
x/"
x."
x-"
x,"
x+"
bx1xxxxxx111111 *"
bx1xxxxxx111111 )"
x("
x'"
x&"
x%"
x$"
x#"
x""
x!"
x~
x}
1|
x{
bx z
xy
xx
xw
xv
1u
1t
1s
1r
xq
xp
xo
xn
xm
xl
xk
xj
1i
xh
xg
xf
xe
xd
xc
xb
1a
x`
x_
1^
bx ]
0\
0[
0Z
xY
xX
1W
1V
xU
xT
bx1xxxxxx111111 S
xR
xQ
0P
0O
bx N
xM
xL
xK
xJ
xI
xH
1G
1F
1E
0D
xC
0B
0A
0@
0?
x>
1=
1<
1;
0:
09
18
07
06
15
14
03
02
11
10
0/
x.
x-
x,
x+
x*
x)
1(
x'
x&
x%
x$
x#
x"
x!
$end
#100
1Y
1D
0<
0;
00
#200
1G"
1c
1B"
bx1xxxx1x1xxxxxx111111 S
bx1xxxx1x1xxxxxx111111 )"
bx1xxxx1x1xxxxxx111111 *"
1h
0{
0C
0%
0'
0*
0)
1X
1?
1@
0D
08
1<
1;
10
#300
0T
1M
1-"
1."
0H
1L
1+"
1/"
0J
0U
0R
b11101 N
b11101 0"
0,"
0K
1E"
13"
0Q
0I
1C"
1e
0D"
1w
1F"
1@"
1<"
1;"
1g
0f
14"
1y
1d
1j
1n
12"
11"
1K"
1J"
1H"
1?"
1>"
1="
1:"
19"
1o
1v
1x
1_
1`
1b
1k
1l
1m
1p
1q
1}
0~
0!"
0""
0#"
0("
1'"
1&"
1%"
1$"
b11110 ]
b11110 z
1G"
1c
1B"
b1111111111011111111111111111 S
b1111111111011111111111111111 )"
b1111111111011111111111111111 *"
1h
1{
1C
0X
0Y
1D
0<
0;
00
#400
1>
0.
1$
0,
0#
0+
0-
1"
0!
1&
0D
1<
1;
10
#500
1D
0<
0;
00
#600
0?
0@
0D
1:
18
1<
1;
10
#700
1Y
1D
0<
0;
00
#800
0M
1T
0L
0+"
1H
1J
b11100 N
b11100 0"
0,"
1R
0E"
1D"
0e
b1111111111101111111111111111 S
b1111111111101111111111111111 )"
b1111111111101111111111111111 *"
1f
0}
1~
1("
0'"
0{
0C
b11101 ]
b11101 z
1X
0D
1<
1;
10
#900
1D
0<
0;
00
#1000
1}
0("
b11100 ]
b11100 z
0$
1,
1-
0"
1!
0&
0D
1<
1;
10
#1100
1D
0<
0;
00
#1200
0D
1<
1;
10
#1300
1D
0<
0;
00
#1400
0D
1<
1;
10
#1500
1D
0<
0;
00
#1600
0D
1<
1;
10
#1700
1D
0<
0;
00
#1800
0D
1<
1;
10
#1900
1D
0<
0;
00
#2000
0D
1<
1;
10
#2100
1D
0<
0;
00
#2200
0D
1<
1;
10
#2300
1D
0<
0;
00
#2400
0D
1<
1;
10
#2500
1D
0<
0;
00
#2600
0D
1<
1;
10
#2700
1D
0<
0;
00
#2800
0D
1<
1;
10
#2900
1D
0<
0;
00
#3000
0D
1<
1;
10
#3100
1D
0<
0;
00
#3200
0D
1<
1;
10
#3300
1D
0<
0;
00
#3400
0D
1<
1;
10
#3500
1D
0<
0;
00
#3600
0D
1<
1;
10
#3700
1D
0<
0;
00
#3800
1A
0V
0D
01
0:
1<
1;
10
