RTL/SCSI_SM/scsi_sm_outputs.v
 /*
// 
// Copyright (C) 2022  Mike Taylor
// This file is part of RE-SDMAC <https://github.com/mbtaylor1982/RE-SDMAC>.
// 
// RE-SDMAC is free software: you can redistribute it and/or modify
// it under the terms of the GNU General Public License as published by
// the Free Software Foundation, either version 3 of the License, or
// (at your option) any later version.
// 
// RE-SDMAC is distributed in the hope that it will be useful,
// but WITHOUT ANY WARRANTY; without even the implied warranty of
// MERCHANTABILITY or FITNESS FOR A PARTICULAR PURPOSE.  See the
// GNU General Public License for more details.
// 
// You should have received a copy of the GNU General Public License
// along with dogtag.  If not, see <http://www.gnu.org/licenses/>.
 */

module scsi_sm_outputs  (
  input [27:0] E_,
  
  output DACK,
  output INCBO,
  output INCNI,
  output INCNO,
  output RE,
  output WE,
  output SCSI_CS,
  output SET_DSACK,
  output S2F,
  output F2S,
  output S2CPU,
  output CPU2S,
  output [4:0] NEXT_STATE
);

  wire scsidff1_d;
  wire scsidff2_d;
  wire scsidff3_d;
  wire scsidff4_d;
  wire scsidff5_d;

  wire E0_;
  wire E1_;
  wire E2_;
  wire E3_;
  wire E4_;
  wire E5_;
  wire E6_;
  wire E7_;
  wire E8_;
  wire E9_;
  wire E10_;
  wire E11_;
  wire E12_;
  wire E13_;
  wire E14_;
  wire E15_;
  wire E16_;
  wire E17_;
  wire E18_;
  wire E19_;
  wire E20_;
  wire E21_;
  wire E22_;
  wire E23_;
  wire E24_;
  wire E25_;
  wire E26_;
  wire E27_;

  assign E0_ = E_[0];
  assign E1_ = E_[1];
  assign E2_ = E_[2];
  assign E3_ = E_[3];
  assign E4_ = E_[4];
  assign E5_ = E_[5];
  assign E6_ = E_[6];
  assign E7_ = E_[7];
  assign E8_ = E_[8];
  assign E9_ = E_[8];
  assign E10_ = E_[10];
  assign E11_ = E_[11];
  assign E12_ = E_[12];
  assign E13_ = E_[13];
  assign E14_ = E_[14];
  assign E15_ = E_[15];
  assign E16_ = E_[16];
  assign E17_ = E_[17];
  assign E18_ = E_[18];
  assign E19_ = E_[19];
  assign E20_ = E_[20];
  assign E21_ = E_[21];
  assign E22_ = E_[22];
  assign E23_ = E_[23];
  assign E24_ = E_[24];
  assign E25_ = E_[25];
  assign E26_ = E_[26];
  assign E27_ = E_[27];


  assign scsidff1_d = ~ (E17_ & E19_ & E23_ & E25_ & E26_ & E8_ & E9_);
  assign scsidff2_d = ~ (~ (E12_ & E13_ & E14_ & E15_ & E16_ & E17_) | ~ (E18_ & E22_ & E24_ & E26_ & E27_));
  assign scsidff3_d = ~ (~ (E0_ & E14_ & E2_ & E7_) | ~ (E15_ & E18_ & E20_ & E21_ & E22_ & E27_));
  assign scsidff4_d = ~ (~ (E0_ & E12_ & E14_ & E15_ & E1_ & E6_) | ~ (E19_ & E20_ & E23_ & E24_ & E25_ & E27_));
  assign scsidff5_d = ~ (~ (E11_ & E13_ & E19_ & E1_ & E5_ & E8_) | ~ (E21_ & E22_ & E23_ & E24_ & E26_ & E27_));

  assign NEXT_STATE = {scsidff5_d, scsidff4_d, scsidff3_d, scsidff2_d, scsidff1_d};
  
  assign DACK = ~ (E0_ & E13_ & E16_ & E1_ & E20_ & E21_ & E7_ & E9_);
  assign INCBO = ~ (E10_ & E11_);
  assign INCNI = ~ (E2_ & E4_);
  assign INCNO = ~ (E2_ & E3_);
  assign RE = ~ (E12_ & E17_ & E20_ & E21_ & E25_ & E26_ & E27_ & E7_);
  assign WE = ~ (E13_ & E16_ & E18_ & E24_ & E8_ & E9_);
  assign SCSI_CS = ~ (~ (E12_ & E17_ & E18_ & E8_) | ~ (E22_ & E24_ & E25_ & E26_ & E27_));
  assign SET_DSACK = ~ (E22_ & E25_);
  assign S2F = ~ (E10_ & E20_ & E21_ & E7_);
  assign F2S = ~ (E11_ & E13_ & E16_ & E9_);
  assign S2CPU = ~ (E12_ & E17_ & E19_ & E23_ & E25_ & E26_ & E27_);
  assign CPU2S = ~ (E18_ & E22_ & E24_ & E8_);

endmodule

RTL/SCSI_SM/scsi_sm_inputs.v
 /*
// 
// Copyright (C) 2022  Mike Taylor
// This file is part of RE-SDMAC <https://github.com/mbtaylor1982/RE-SDMAC>.
// 
// RE-SDMAC is free software: you can redistribute it and/or modify
// it under the terms of the GNU General Public License as published by
// the Free Software Foundation, either version 3 of the License, or
// (at your option) any later version.
// 
// RE-SDMAC is distributed in the hope that it will be useful,
// but WITHOUT ANY WARRANTY; without even the implied warranty of
// MERCHANTABILITY or FITNESS FOR A PARTICULAR PURPOSE.  See the
// GNU General Public License for more details.
// 
// You should have received a copy of the GNU General Public License
// along with dogtag.  If not, see <http://www.gnu.org/licenses/>.
 */

module scsi_sm_inputs(
  input [4:0] STATE,   
  input BOEQ3,
  input CCPUREQ,
  input CDREQ_,
  input CDSACK_,
  input DMADIR,
  input FIFOEMPTY,
  input FIFOFULL,
  input RDFIFO_o,
  input RIFIFO_o,
  input RW,

  output [27:0] E_
);
  wire nCDSACK_;
  wire nDMADIR;

  wire scsidff1_q;
  wire scsidff2_q;
  wire scsidff3_q;
  wire scsidff4_q;
  wire scsidff5_q; 
  
  wire nscsidff1_q;
  wire nscsidff2_q;
  wire nscsidff3_q;
  wire nscsidff4_q;
  wire nscsidff5_q;

  wire E0_;
  wire E1_;
  wire E2_;
  wire E3_;
  wire E4_;
  wire E5_;
  wire E6_;
  wire E7_;
  wire E8_;
  wire E9_;
  wire E10_;
  wire E11_;
  wire E12_;
  wire E13_;
  wire E14_;
  wire E15_;
  wire E16_;
  wire E17_;
  wire E18_;
  wire E19_;
  wire E20_;
  wire E21_;
  wire E22_;
  wire E23_;
  wire E24_;
  wire E25_;
  wire E26_;
  wire E27_;
    
  assign nCDSACK_ = ~ CDSACK_;
  assign nDMADIR = ~ DMADIR;

  assign scsidff1_q = STATE[0];
  assign scsidff2_q = STATE[1];
  assign scsidff3_q = STATE[2];
  assign scsidff4_q = STATE[3];
  assign scsidff5_q = STATE[4];

  assign nscsidff1_q = ~ scsidff1_q;
  assign nscsidff2_q = ~ scsidff2_q;
  assign nscsidff3_q = ~ scsidff3_q;
  assign nscsidff4_q = ~ scsidff4_q;
  assign nscsidff5_q = ~ scsidff5_q;

  assign E1_ = ~ (~ (CCPUREQ | CDREQ_ | nDMADIR | FIFOFULL | RIFIFO_o | scsidff1_q | scsidff2_q | scsidff4_q) & nscsidff3_q & nscsidff5_q);
  assign E0_ = ~ (~ (CCPUREQ | CDREQ_ | DMADIR | FIFOEMPTY | RDFIFO_o | scsidff1_q | scsidff2_q | scsidff4_q) & scsidff5_q);
  assign E2_ = ~ (FIFOFULL & nscsidff1_q & nscsidff2_q & nscsidff3_q & scsidff4_q & scsidff5_q);
  assign E3_ = ~ (BOEQ3 & scsidff1_q & nscsidff2_q & nscsidff4_q & nscsidff5_q);
  assign E4_ = ~ (BOEQ3 & nscsidff2_q & scsidff3_q & scsidff4_q & nscsidff5_q);
  assign E5_ = ~ (~ CCPUREQ & nDMADIR & nscsidff2_q & nscsidff3_q & nscsidff4_q);
  assign E6_ = ~ (CCPUREQ & nscsidff1_q & nscsidff2_q & nscsidff3_q & nscsidff4_q);
  assign E7_ = ~ (~ FIFOFULL & nscsidff1_q & nscsidff2_q & nscsidff3_q & scsidff4_q & scsidff5_q);
  assign E8_ = ~ (~ RW & nscsidff1_q & nscsidff2_q & nscsidff3_q & scsidff4_q & nscsidff5_q);
  assign E9_ = ~ (nscsidff1_q & scsidff2_q & nscsidff3_q & nscsidff4_q & scsidff5_q);
  assign E10_ = ~ (nscsidff2_q & scsidff3_q & scsidff4_q & nscsidff5_q);
  assign E11_ = ~ (scsidff1_q & nscsidff2_q & nscsidff4_q & nscsidff5_q);
  assign E12_ = ~ (RW & nscsidff1_q & nscsidff3_q & scsidff4_q & nscsidff5_q);
  assign E13_ = ~ (nscsidff1_q & scsidff2_q & nscsidff3_q & nscsidff4_q & nscsidff5_q);
  assign E14_ = ~ (nCDSACK_ & scsidff2_q & scsidff4_q & nscsidff5_q);
  assign E15_ = ~ (scsidff2_q & scsidff3_q & nscsidff4_q & scsidff5_q);
  assign E16_ = ~ (nscsidff2_q & scsidff3_q & scsidff4_q & scsidff5_q);
  assign E17_ = ~ (scsidff2_q & scsidff3_q & scsidff4_q & scsidff5_q);
  assign E18_ = ~ (scsidff2_q & nscsidff3_q & scsidff4_q & scsidff5_q);
  assign E19_ = ~ (nCDSACK_ & scsidff1_q & scsidff4_q);
  assign E20_ = ~ (nscsidff2_q & scsidff3_q & nscsidff4_q & scsidff5_q);
  assign E21_ = ~ (nscsidff2_q & scsidff3_q & nscsidff4_q & nscsidff5_q);
  assign E22_ = ~ (scsidff2_q & scsidff3_q & nscsidff4_q & nscsidff5_q);
  assign E23_ = ~ (scsidff1_q & scsidff4_q & nscsidff5_q);
  assign E24_ = ~ (scsidff1_q & nscsidff2_q & nscsidff4_q & scsidff5_q);
  assign E25_ = ~ (scsidff1_q & scsidff2_q & scsidff5_q);
  assign E26_ = ~ (scsidff1_q & scsidff2_q & nscsidff5_q);
  assign E27_ = ~ (scsidff2_q & nscsidff3_q & scsidff4_q & nscsidff5_q);

  assign E_[27:0] = {E27_,E26_,E25_,E24_,E23_,E22_,E21_,E20_,E19_,E18_,E17_,E16_,E15_,E14_,E13_,E12_,E11_,E10_,E9_,E8_,E7_,E6_,E5_,E4_,E3_,E2_,E1_,E0_};
  
endmodule

RTL/SCSI_SM/SCSI_SM.v
 /*
// 
// Copyright (C) 2022  Mike Taylor
// This file is part of RE-SDMAC <https://github.com/mbtaylor1982/RE-SDMAC>.
// 
// RE-SDMAC is free software: you can redistribute it and/or modify
// it under the terms of the GNU General Public License as published by
// the Free Software Foundation, either version 3 of the License, or
// (at your option) any later version.
// 
// RE-SDMAC is distributed in the hope that it will be useful,
// but WITHOUT ANY WARRANTY; without even the implied warranty of
// MERCHANTABILITY or FITNESS FOR A PARTICULAR PURPOSE.  See the
// GNU General Public License for more details.
// 
// You should have received a copy of the GNU General Public License
// along with dogtag.  If not, see <http://www.gnu.org/licenses/>.
 */

 `include "RTL/SCSI_SM/scsi_sm_inputs.v"
 `include "RTL/SCSI_SM/scsi_sm_outputs.v"

module SCSI_SM(
    input DSACK_,
    input CPUREQ,
    input RW,
    input DMADIR,    
    input RDFIFO_o,
    input RIFIFO_o,
    input RESET_,
    input BOEQ3,
    input CPUCLK,
    input DREQ_,
    input FIFOFULL,
    input FIFOEMPTY,

    output SET_DSACK,
    output reg RDFIFO_d,
    output reg RIFIFO_d,
    output reg RE_o,
    output reg WE_o,
    output reg SCSI_CS_o,
    output reg DACK_o,
    output reg INCBO_o,
    output reg INCNO_o,
    output reg INCNI_o,
    output reg S2F_o,
    output reg F2S_o,
    output reg S2CPU_o,
    output reg CPU2S_o
);

localparam INITIAL_STATE = 5'b11110;

reg [4:0] STATE;

//Clocked inputs
reg CCPUREQ;
reg CDREQ_;
reg CDSACK_;
reg CRESET_;

wire RE;
wire WE;
wire SCSI_CS;
wire DACK;
wire INCBO;
wire INCNO;
wire INCNI;
wire S2F;
wire F2S;
wire S2CPU;
wire CPU2S;

wire nRW;
wire nDMADIR;
wire nFIFOFULL;
wire nCCPUREQ;
wire nCDREQ_;
wire nCDSACK_;

wire nCLK; // CPUCLK Inverted
wire BCLK; // CPUCLK Inverted 4 times for delay.
wire BBCLK; // CPUCLK Inverted 6 time for delay.

wire [27:0] E_;
wire [4:0] NEXT_STATE;

scsi_sm_inputs u_scsi_sm_inputs(
    .STATE      (STATE),
    .BOEQ3      (BOEQ3      ),
    .CCPUREQ    (CCPUREQ    ),
    .CDREQ_     (CDREQ_     ),
    .CDSACK_    (CDSACK_    ),
    .DMADIR     (DMADIR     ),
    .FIFOEMPTY  (FIFOEMPTY  ),
    .FIFOFULL   (FIFOFULL   ),
    .RDFIFO_o   (RDFIFO_o   ),
    .RIFIFO_o   (RIFIFO_o   ),
    .RW         (RW         ),
    .E_         (E_         )
);

scsi_sm_outputs u_scsi_sm_outputs(
    .E_         (E_         ),
    .NEXT_STATE (NEXT_STATE ), 
    .DACK       (DACK       ),
    .INCBO      (INCBO      ),
    .INCNI      (INCNI      ),
    .INCNO      (INCNO      ),
    .RE         (RE         ),
    .WE         (WE         ),
    .SCSI_CS    (SCSI_CS    ),
    .SET_DSACK  (SET_DSACK  ),
    .S2F        (S2F        ),
    .F2S        (F2S        ),
    .S2CPU      (S2CPU      ),
    .CPU2S      (CPU2S      )
);

//clocked reset
always @(posedge  nCLK) begin
    CRESET_ <= RESET_;

    if(RESET_ == 1'b0) begin     
        CDSACK_ <= 1'b0;
    end
end

//clocked inputs.
always @(posedge  BBCLK or negedge CRESET_) begin
    if (CRESET_ == 1'b0) 
        CDSACK_ <= 1'b0;
    else 
    begin
        CCPUREQ <= CPUREQ;
        CDREQ_ <= DREQ_;
        CDSACK_ <= DSACK_;   
    end
end

//Clocked outputs.
always @(posedge BCLK) begin
    RE_o <= RE;
    WE_o <= WE;
    SCSI_CS_o <= ~SCSI_CS;
    DACK_o <= DACK;
    INCBO_o <= INCBO;
    INCNO_o <= INCNO;
    INCNI_o <= INCNI;
    S2F_o <= S2F;
    F2S_o <= F2S;
    S2CPU_o <= S2CPU;
    CPU2S_o <= CPU2S;   
    RDFIFO_d <= ~E_[3];
    RIFIFO_d <=  ~E_[4];
end

//State Machine
always @(posedge BCLK or negedge CRESET_) begin
    if (CRESET_ == 1'b0) 
        STATE <= INITIAL_STATE;
    else
        STATE <= NEXT_STATE;
end

assign nCLK = ~CPUCLK;
assign BCLK = CPUCLK; // may need to change this to add delays
assign BBCLK = CPUCLK; // may need to change this to add delays

assign nRW = ~RW;
assign nDMADIR = ~DMADIR;
assign nFIFOFULL = ~FIFOFULL;
assign nCCPUREQ = ~CCPUREQ;
assign nCDREQ_ = ~CDREQ_;
assign nCDSACK_ = ~CDSACK_;


endmodule

RTL/SCSI_SM/Testbench/SCSI_SM_tb.v
 /*
// 
// Copyright (C) 2022  Mike Taylor
// This file is part of RE-SDMAC <https://github.com/mbtaylor1982/RE-SDMAC>.
// 
// RE-SDMAC is free software: you can redistribute it and/or modify
// it under the terms of the GNU General Public License as published by
// the Free Software Foundation, either version 3 of the License, or
// (at your option) any later version.
// 
// RE-SDMAC is distributed in the hope that it will be useful,
// but WITHOUT ANY WARRANTY; without even the implied warranty of
// MERCHANTABILITY or FITNESS FOR A PARTICULAR PURPOSE.  See the
// GNU General Public License for more details.
// 
// You should have received a copy of the GNU General Public License
// along with dogtag.  If not, see <http://www.gnu.org/licenses/>.
 */

`timescale 1ns/100ps

`include "RTL/SCSI_SM/SCSI_SM.v"

module scsi_sm_tb; 
//inputs
reg DSACK_;
reg CPUREQ;
reg RW;
reg DMADIR;
reg RDFIFO;
reg RIFIFO;
reg RESET_;
reg BOEQ3;
reg CPUCLK;
reg DREQ_;
reg FIFOFULL;
reg FIFOEMPTY;

//Outputs
wire SET_DSACK;
wire RDFIFO_d;
wire RIFIFO_d;
wire RE_o;
wire WE_o;
wire SCSI_CS_o;
wire DACK_o;
wire INCBO_o;
wire INCNO_o;
wire INCNI_o;
wire S2F_o;
wire F2S_o;
wire S2CPU_o;
wire CPU2S_o;


SCSI_SM u_SCSI_SM(
    .DSACK_    (DSACK_    ),
    .CPUREQ    (CPUREQ    ),
    .RW        (RW        ),
    .DMADIR    (DMADIR    ),
    .RDFIFO_o  (RDFIFO_o  ),
    .RIFIFO_o  (RIFIFO_o  ),
    .RESET_    (RESET_    ),
    .BOEQ3     (BOEQ3     ),
    .CPUCLK    (CPUCLK    ),
    .DREQ_     (DREQ_     ),
    .FIFOFULL  (FIFOFULL  ),
    .FIFOEMPTY (FIFOEMPTY ),
    .SET_DSACK (SET_DSACK ),
    .RDFIFO_d  (RDFIFO_d  ),
    .RIFIFO_d  (RIFIFO_d  ),
    .RE_o      (RE_o      ),
    .WE_o      (WE_o      ),
    .SCSI_CS_o (SCSI_CS_o ),
    .DACK_o    (DACK_o    ),
    .INCBO_o   (INCBO_o   ),
    .INCNO_o   (INCNO_o   ),
    .INCNI_o   (INCNI_o   ),
    .S2F_o     (S2F_o     ),
    .F2S_o     (F2S_o     ),
    .S2CPU_o   (S2CPU_o   ),
    .CPU2S_o   (CPU2S_o   )
);

    initial begin
        $display("*Testing SDMAC SCSI_SM.v Module*");
        $dumpfile("../SCSI_SM/VCD/SCSI_SM_tb.vcd");
        $dumpvars(0, scsi_sm_tb);
        
        //test FIFO Full Empty Counter
        $display("Testing SCSI State Machine RESET");
        //set initial state
        CPUCLK = 1'b1;
        CPUREQ = 1'b1;
        RESET_ = 1'b1;
        DSACK_ = 1'b0;
        RW = 1'b1;
        DMADIR = 1'b0;
        RDFIFO = 1'b0;
        RIFIFO = 1'b0;
        BOEQ3 = 1'b0;
        DREQ_ = 1'b1;
        FIFOFULL = 1'b0;
        FIFOEMPTY = 1'b1;
        repeat(2) #10 CPUCLK = ~CPUCLK;
        RESET_ = 1'b0;
        repeat(4) #10 CPUCLK = ~CPUCLK;
        RESET_ = 1'b1;
        repeat(32) #10 CPUCLK = ~CPUCLK;
        $finish;
    end 

endmodule

RTL/SCSI_SM/VCD/SCSI_SM_tb.vcd
$date
	Sat Nov 19 17:32:56 2022
$end
$version
	Icarus Verilog
$end
$timescale
	100ps
$end
$scope module scsi_sm_tb $end
$var wire 1 ! RDFIFO_o $end
$var wire 1 " RIFIFO_o $end
$var wire 1 # WE_o $end
$var wire 1 $ SET_DSACK $end
$var wire 1 % SCSI_CS_o $end
$var wire 1 & S2F_o $end
$var wire 1 ' S2CPU_o $end
$var wire 1 ( RIFIFO_d $end
$var wire 1 ) RE_o $end
$var wire 1 * RDFIFO_d $end
$var wire 1 + INCNO_o $end
$var wire 1 , INCNI_o $end
$var wire 1 - INCBO_o $end
$var wire 1 . F2S_o $end
$var wire 1 / DACK_o $end
$var wire 1 0 CPU2S_o $end
$var reg 1 1 BOEQ3 $end
$var reg 1 2 CPUCLK $end
$var reg 1 3 CPUREQ $end
$var reg 1 4 DMADIR $end
$var reg 1 5 DREQ_ $end
$var reg 1 6 DSACK_ $end
$var reg 1 7 FIFOEMPTY $end
$var reg 1 8 FIFOFULL $end
$var reg 1 9 RDFIFO $end
$var reg 1 : RESET_ $end
$var reg 1 ; RIFIFO $end
$var reg 1 < RW $end
$scope module u_SCSI_SM $end
$var wire 1 = BBCLK $end
$var wire 1 > BCLK $end
$var wire 1 1 BOEQ3 $end
$var wire 1 2 CPUCLK $end
$var wire 1 3 CPUREQ $end
$var wire 1 4 DMADIR $end
$var wire 1 5 DREQ_ $end
$var wire 1 6 DSACK_ $end
$var wire 1 7 FIFOEMPTY $end
$var wire 1 8 FIFOFULL $end
$var wire 1 ! RDFIFO_o $end
$var wire 1 : RESET_ $end
$var wire 1 " RIFIFO_o $end
$var wire 1 < RW $end
$var wire 1 ? nCCPUREQ $end
$var wire 1 @ nCDREQ_ $end
$var wire 1 A nCDSACK_ $end
$var wire 1 B nCLK $end
$var wire 1 C nDMADIR $end
$var wire 1 D nFIFOFULL $end
$var wire 1 E nRW $end
$var wire 1 F WE $end
$var wire 1 $ SET_DSACK $end
$var wire 1 G SCSI_CS $end
$var wire 1 H S2F $end
$var wire 1 I S2CPU $end
$var wire 1 J RE $end
$var wire 5 K NEXT_STATE [4:0] $end
$var wire 1 L INCNO $end
$var wire 1 M INCNI $end
$var wire 1 N INCBO $end
$var wire 1 O F2S $end
$var wire 28 P E_ [27:0] $end
$var wire 1 Q DACK $end
$var wire 1 R CPU2S $end
$var reg 1 S CCPUREQ $end
$var reg 1 T CDREQ_ $end
$var reg 1 U CDSACK_ $end
$var reg 1 0 CPU2S_o $end
$var reg 1 V CRESET_ $end
$var reg 1 / DACK_o $end
$var reg 1 . F2S_o $end
$var reg 1 - INCBO_o $end
$var reg 1 , INCNI_o $end
$var reg 1 + INCNO_o $end
$var reg 1 * RDFIFO_d $end
$var reg 1 ) RE_o $end
$var reg 1 ( RIFIFO_d $end
$var reg 1 ' S2CPU_o $end
$var reg 1 & S2F_o $end
$var reg 1 % SCSI_CS_o $end
$var reg 5 W STATE [4:0] $end
$var reg 1 # WE_o $end
$scope module u_scsi_sm_inputs $end
$var wire 1 1 BOEQ3 $end
$var wire 1 S CCPUREQ $end
$var wire 1 T CDREQ_ $end
$var wire 1 U CDSACK_ $end
$var wire 1 4 DMADIR $end
$var wire 1 X E0_ $end
$var wire 1 Y E10_ $end
$var wire 1 Z E11_ $end
$var wire 1 [ E12_ $end
$var wire 1 \ E13_ $end
$var wire 1 ] E14_ $end
$var wire 1 ^ E15_ $end
$var wire 1 _ E16_ $end
$var wire 1 ` E17_ $end
$var wire 1 a E18_ $end
$var wire 1 b E19_ $end
$var wire 1 c E1_ $end
$var wire 1 d E20_ $end
$var wire 1 e E21_ $end
$var wire 1 f E22_ $end
$var wire 1 g E23_ $end
$var wire 1 h E24_ $end
$var wire 1 i E25_ $end
$var wire 1 j E26_ $end
$var wire 1 k E27_ $end
$var wire 1 l E2_ $end
$var wire 1 m E3_ $end
$var wire 1 n E4_ $end
$var wire 1 o E5_ $end
$var wire 1 p E6_ $end
$var wire 1 q E7_ $end
$var wire 1 r E8_ $end
$var wire 1 s E9_ $end
$var wire 1 7 FIFOEMPTY $end
$var wire 1 8 FIFOFULL $end
$var wire 1 ! RDFIFO_o $end
$var wire 1 " RIFIFO_o $end
$var wire 1 < RW $end
$var wire 5 t STATE [4:0] $end
$var wire 1 u nCDSACK_ $end
$var wire 1 v nDMADIR $end
$var wire 1 w nscsidff1_q $end
$var wire 1 x nscsidff2_q $end
$var wire 1 y nscsidff3_q $end
$var wire 1 z nscsidff4_q $end
$var wire 1 { nscsidff5_q $end
$var wire 1 | scsidff5_q $end
$var wire 1 } scsidff4_q $end
$var wire 1 ~ scsidff3_q $end
$var wire 1 !" scsidff2_q $end
$var wire 1 "" scsidff1_q $end
$var wire 28 #" E_ [27:0] $end
$upscope $end
$scope module u_scsi_sm_outputs $end
$var wire 1 R CPU2S $end
$var wire 1 Q DACK $end
$var wire 28 $" E_ [27:0] $end
$var wire 1 O F2S $end
$var wire 1 N INCBO $end
$var wire 1 M INCNI $end
$var wire 1 L INCNO $end
$var wire 1 J RE $end
$var wire 1 I S2CPU $end
$var wire 1 H S2F $end
$var wire 1 G SCSI_CS $end
$var wire 1 $ SET_DSACK $end
$var wire 1 F WE $end
$var wire 1 %" scsidff1_d $end
$var wire 1 &" scsidff2_d $end
$var wire 1 '" scsidff3_d $end
$var wire 1 (" scsidff4_d $end
$var wire 1 )" scsidff5_d $end
$var wire 5 *" NEXT_STATE [4:0] $end
$var wire 1 +" E9_ $end
$var wire 1 ," E8_ $end
$var wire 1 -" E7_ $end
$var wire 1 ." E6_ $end
$var wire 1 /" E5_ $end
$var wire 1 0" E4_ $end
$var wire 1 1" E3_ $end
$var wire 1 2" E2_ $end
$var wire 1 3" E27_ $end
$var wire 1 4" E26_ $end
$var wire 1 5" E25_ $end
$var wire 1 6" E24_ $end
$var wire 1 7" E23_ $end
$var wire 1 8" E22_ $end
$var wire 1 9" E21_ $end
$var wire 1 :" E20_ $end
$var wire 1 ;" E1_ $end
$var wire 1 <" E19_ $end
$var wire 1 =" E18_ $end
$var wire 1 >" E17_ $end
$var wire 1 ?" E16_ $end
$var wire 1 @" E15_ $end
$var wire 1 A" E14_ $end
$var wire 1 B" E13_ $end
$var wire 1 C" E12_ $end
$var wire 1 D" E11_ $end
$var wire 1 E" E10_ $end
$var wire 1 F" E0_ $end
$upscope $end
$upscope $end
$upscope $end
$enddefinitions $end
#0
$dumpvars
1F"
xE"
xD"
xC"
xB"
xA"
x@"
x?"
x>"
x="
x<"
1;"
x:"
x9"
x8"
x7"
x6"
x5"
x4"
x3"
12"
11"
10"
1/"
x."
x-"
1,"
1+"
bx *"
x)"
x("
x'"
x&"
x%"
bx1xx111111 $"
bx1xx111111 #"
x""
x!"
x~
x}
x|
x{
xz
xy
xx
xw
1v
1u
bx t
xs
1r
xq
xp
1o
1n
1m
1l
xk
xj
xi
xh
xg
xf
xe
xd
1c
xb
xa
x`
x_
x^
x]
x\
x[
xZ
xY
1X
bx W
xV
0U
1T
1S
xR
xQ
bx1xx111111 P
xO
xN
0M
0L
bx K
xJ
xI
xH
xG
xF
0E
1D
1C
0B
1A
0@
0?
1>
1=
1<
0;
1:
09
08
17
06
15
04
13
12
01
x0
x/
x.
x-
x,
x+
x*
x)
x(
x'
x&
x%
x$
x#
z"
z!
$end
#100
1V
1B
0>
0=
02
#200
0(
0*
0,
0+
0B
0:
1>
1=
12
#300
0Q
1J
1'"
1("
0F
1I
1%"
1)"
0G
0R
0O
b11101 K
b11101 *"
0&"
0H
1?"
1-"
0N
0$
1="
1_
0>"
1q
1@"
1:"
16"
1<"
15"
1a
0`
1."
1s
1^
1d
1h
1E"
1D"
1C"
1B"
1A"
19"
18"
17"
14"
13"
1b
1i
1p
1Y
1Z
1[
1\
1]
1e
1f
1g
1j
b1111111111011111111111111111 P
b1111111111011111111111111111 #"
b1111111111011111111111111111 $"
1k
1w
0x
0y
0z
0{
0""
1!"
1~
1}
1|
b11110 W
b11110 t
0V
1B
0>
0=
02
#400
00
1'
0.
0&
0-
0/
1%
0#
1)
0B
1>
1=
12
#500
1B
0>
0=
02
#600
0B
1:
1>
1=
12
#700
1V
1B
0>
0=
02
#800
0J
1Q
0("
1F
0)"
1G
b101 K
b101 *"
0&"
1O
0?"
1>"
0_
0<"
1`
b1111111101101111111111111111 P
b1111111101101111111111111111 #"
b1111111101101111111111111111 $"
0b
0w
1x
1""
0!"
b11101 W
b11101 t
0B
1>
1=
12
#900
1B
0>
0=
02
#1000
1("
1J
0'"
0)"
0%"
0I
0F
1H
b1010 K
b1010 *"
1&"
1N
1O
0D"
09"
0Z
0e
1<"
1?"
1b
b1111110111111111011111111111 P
b1111110111111111011111111111 #"
b1111110111111111011111111111 $"
1_
1z
1{
0}
0|
b101 W
b101 t
1.
1/
0%
1#
0)
0B
1>
1=
12
#1100
1B
0>
0=
02
#1200
0%"
0G
0("
b0 K
b0 *"
0&"
0H
0O
0Q
0C"
1I
0N
0[
03"
0A"
1D"
19"
0k
0]
1E"
1Z
1e
1<"
1Y
b111111111111010111111111111 P
b111111111111010111111111111 #"
b111111111111010111111111111 $"
1b
1w
0x
1y
0z
0""
1!"
0~
1}
b1010 W
b1010 t
0'
1&
1-
0#
1)
0B
1>
1=
12
#1300
1B
0>
0=
02
#1400
1&"
0Q
0J
0I
0F
1'"
1G
0O
b10110 K
b10110 *"
1)"
0."
0p
1B"
13"
1A"
1C"
1\
1k
1]
b1111111111111111111110111111 P
b1111111111111111111110111111 #"
b1111111111111111111110111111 $"
1[
1x
1z
0!"
0}
b0 W
b0 t
1'
0.
0&
0-
0/
1%
0B
1>
1=
12
#1500
1B
0>
0=
02
#1600
0J
0'"
0&"
0Q
0H
b10000 K
b10000 *"
0("
1:"
0@"
1."
1d
0^
b1111111111110111111111111111 P
b1111111111110111111111111111 #"
b1111111111110111111111111111 $"
1p
0x
0y
0{
1!"
1~
1|
b10110 W
b10110 t
0'
0%
0)
0B
1>
1=
12
#1700
1B
0>
0=
02
#1800
1'"
b10110 K
b10110 *"
1&"
0."
0p
1@"
b1111111111111111111110111111 P
b1111111111111111111110111111 #"
b1111111111111111111110111111 $"
1^
1x
1y
0!"
0~
b10000 W
b10000 t
0B
1>
1=
12
#1900
1B
0>
0=
02
#2000
0J
0'"
0&"
0Q
0H
b10000 K
b10000 *"
0("
1:"
0@"
1."
1d
0^
b1111111111110111111111111111 P
b1111111111110111111111111111 #"
b1111111111110111111111111111 $"
1p
0x
0y
1!"
1~
b10110 W
b10110 t
0B
1>
1=
12
#2100
1B
0>
0=
02
#2200
1'"
b10110 K
b10110 *"
1&"
0."
0p
1@"
b1111111111111111111110111111 P
b1111111111111111111110111111 #"
b1111111111111111111110111111 $"
1^
1x
1y
0!"
0~
b10000 W
b10000 t
0B
1>
1=
12
#2300
1B
0>
0=
02
#2400
0J
0'"
0&"
0Q
0H
b10000 K
b10000 *"
0("
1:"
0@"
1."
1d
0^
b1111111111110111111111111111 P
b1111111111110111111111111111 #"
b1111111111110111111111111111 $"
1p
0x
0y
1!"
1~
b10110 W
b10110 t
0B
1>
1=
12
#2500
1B
0>
0=
02
#2600
1'"
b10110 K
b10110 *"
1&"
0."
0p
1@"
b1111111111111111111110111111 P
b1111111111111111111110111111 #"
b1111111111111111111110111111 $"
1^
1x
1y
0!"
0~
b10000 W
b10000 t
0B
1>
1=
12
#2700
1B
0>
0=
02
#2800
0J
0'"
0&"
0Q
0H
b10000 K
b10000 *"
0("
1:"
0@"
1."
1d
0^
b1111111111110111111111111111 P
b1111111111110111111111111111 #"
b1111111111110111111111111111 $"
1p
0x
0y
1!"
1~
b10110 W
b10110 t
0B
1>
1=
12
#2900
1B
0>
0=
02
#3000
1'"
b10110 K
b10110 *"
1&"
0."
0p
1@"
b1111111111111111111110111111 P
b1111111111111111111110111111 #"
b1111111111111111111110111111 $"
1^
1x
1y
0!"
0~
b10000 W
b10000 t
0B
1>
1=
12
#3100
1B
0>
0=
02
#3200
0J
0'"
0&"
0Q
0H
b10000 K
b10000 *"
0("
1:"
0@"
1."
1d
0^
b1111111111110111111111111111 P
b1111111111110111111111111111 #"
b1111111111110111111111111111 $"
1p
0x
0y
1!"
1~
b10110 W
b10110 t
0B
1>
1=
12
#3300
1B
0>
0=
02
#3400
1'"
b10110 K
b10110 *"
1&"
0."
0p
1@"
b1111111111111111111110111111 P
b1111111111111111111110111111 #"
b1111111111111111111110111111 $"
1^
1x
1y
0!"
0~
b10000 W
b10000 t
0B
1>
1=
12
#3500
1B
0>
0=
02
